plutex/__init__.py
plutex/backtester.py
plutex/cli.py
plutex/main.py
plutex/agents/ben_graham.py
plutex/agents/bill_ackman.py
plutex/agents/cathie_wood.py
plutex/agents/charlie_munger.py
plutex/agents/fundamentals.py
plutex/agents/michael_burry.py
plutex/agents/peter_lynch.py
plutex/agents/phil_fisher.py
plutex/agents/portfolio_manager.py
plutex/agents/risk_manager.py
plutex/agents/sentiment.py
plutex/agents/stanley_druckenmiller.py
plutex/agents/technicals.py
plutex/agents/valuation.py
plutex/agents/warren_buffett.py
plutex/data/cache.py
plutex/data/models.py
plutex/graph/__init__.py
plutex/graph/state.py
plutex/llm/__init__.py
plutex/llm/models.py
plutex/tools/__init__.py
plutex/tools/api.py
plutex/utils/__init__.py
plutex/utils/analysts.py
plutex/utils/display.py
plutex/utils/llm.py
plutex/utils/progress.py
plutex/utils/visualize.py
plutex-0.2.1.dist-info/METADATA
plutex-0.2.1.dist-info/WHEEL
plutex-0.2.1.dist-info/entry_points.txt
plutex-0.2.1.dist-info/licenses/LICENSE
plutex-0.2.1.dist-info/RECORD
