Metadata-Version: 2.4
Name: plutex
Version: 0.2.1
Summary: plutex: An AI-powered trading system using multiple agents
Author-email: Shane Holloman <shaneholloman@gmail.com>
License-File: LICENSE
Requires-Python: >=3.11
Requires-Dist: colorama<0.5,>=0.4.6
Requires-Dist: langchain-anthropic==0.3.5
Requires-Dist: langchain-deepseek<0.2,>=0.1.2
Requires-Dist: langchain-google-genai<3,>=2.0.11
Requires-Dist: langchain-groq==0.2.3
Requires-Dist: langchain-openai<0.4,>=0.3.5
Requires-Dist: langchain==0.3.0
Requires-Dist: langgraph==0.2.56
Requires-Dist: matplotlib<4,>=3.9.2
Requires-Dist: numpy<2,>=1.24.0
Requires-Dist: pandas<3,>=2.1.0
Requires-Dist: python-dotenv
Requires-Dist: questionary<3,>=2.1.0
Requires-Dist: rich<14,>=13.9.4
Requires-Dist: tabulate<0.10,>=0.9.0
